{
  "apps": {
    "nvim": {
      "paths": [
        {
          "internal": "data/nvim/init.lua",
          "external": "~/.config/nvim/init.lua"
        }
      ]
    },
    "tmux": {
      "paths": [
        {
          "internal": "data/tmux/tmux.conf",
          "external": "~/.config/tmux/tmux.conf"
        }
      ]
    },
    "kitty": {
      "paths": [
        {
          "internal": "data/kitty",
          "external": "~/.config/kitty"
        }
      ]
    },
    "bat": {
      "paths": [
        {
          "internal": "data/bat",
          "external": "~/.config/bat"
        }
      ]
    },
    "fd": {
      "paths": [
        {
          "internal": "data/fd/.ignore",
          "external": "~/.ignore"
        }
      ]
    }
  }
}
